README.rst
setup.py
SendRequest/SendRequest.py
SendRequest/__init__.py
SendRequest.egg-info/PKG-INFO
SendRequest.egg-info/SOURCES.txt
SendRequest.egg-info/dependency_links.txt
SendRequest.egg-info/top_level.txt