Metadata-Version: 1.0
Name: SendRequest
Version: 0.3
Summary: http request with retry, download pic.封装网络请求，自带重试
Home-page: UNKNOWN
Author: UNKNOWN
Author-email: UNKNOWN
License: UNKNOWN
Platform: UNKNOWN
